{
    "home": {
        "path": "/",
        "defaults": {
            "_controller": "\\Trillium\\Controller\\Home",
            "_action": "index"
        }
    },
    "user.sign.in": {
      "path": "/user/sign/in",
      "defaults": {
          "_controller": "\\Trillium\\Controller\\User",
          "_action": "signIn"
      }
    },
    "user.sign.in.check": {
        "path": "/user/sign/in/check",
        "defaults": {
            "_controller": null
        }
    },
    "user.sign.out": {
        "path": "/user/sign/out",
        "defaults": {
            "_controller": "\\Trillium\\Controller\\User",
            "_action": "signOut"
        }
    },
    "user.edit.password": {
        "path": "/user/edit/password/{username}",
        "defaults": {
            "_controller": "\\Trillium\\Controller\\User",
            "_action": "editPassword",
            "username": ""
        }
    },
    "user.is_authorized": {
        "path": "/user/is_authorized",
        "defaults": {
            "_controller": "\\Trillium\\Controller\\User",
            "_action": "isAuthorized"
        }
    },
    "user.listing": {
        "path": "/user/listing",
        "defaults": {
            "_controller": "\\Trillium\\Controller\\User",
            "_action": "listing"
        }
    },
    "user.create": {
        "path": "/user/create",
        "defaults": {
            "_controller": "\\Trillium\\Controller\\User",
            "_action": "create"
        }
    }
}